mantis_catalog/__init__.py
mantis_catalog/config.py
mantis_catalog/path.py
mantis_catalog-0.1.2.dist-info/METADATA
mantis_catalog-0.1.2.dist-info/WHEEL
mantis_catalog-0.1.2.dist-info/RECORD
