Metadata-Version: 2.1
Name: mantis-catalog
Version: 0.1.2
Summary: M&NTIS library to manipulate catalog of resources
License: MIT
Author: AMOSSYS
Requires-Python: >=3.10,<4.0
Classifier: License :: OSI Approved :: MIT License
Classifier: Programming Language :: Python :: 3
Classifier: Programming Language :: Python :: 3.10
Classifier: Programming Language :: Python :: 3.11
Classifier: Programming Language :: Python :: 3.12
Classifier: Programming Language :: Python :: 3.13
Requires-Dist: fsspec[s3]
Requires-Dist: omegaconf
Requires-Dist: universal-pathlib (>=0.2.6,<0.3.0)
